{"keyframes":{"0":{"elements":[{"id":"0","text":"","width":{"width":1469},"height":{"height":89},"x":{"left":4,"right":7},"y":{"top":4,"bottom":707},"font-size":{"font-size":16},"background-color":{"background-color":{"r":12,"g":50,"b":84}}},{"id":"1","text":"","width":{"width":1468},"height":{"height":35},"x":{"left":4,"right":8},"y":{"top":94,"bottom":671},"font-size":{"font-size":16},"background-color":{"background-color":{"r":56,"g":82,"b":109}}},{"id":"2","text":"","image":"images/cse_logo.png","width":{"width":430},"height":{"height":82},"x":{"left":233,"right":816},"y":{"top":7,"bottom":711},"font-size":{"font-size":16},"background-color":{"background-color":{"r":255,"g":255,"b":255}}},{"id":"3","text":"ACADEMICS+ADMISSIONS","width":{"width":208},"height":{"height":21},"x":{"left":234,"right":1036},"y":{"top":99,"bottom":680},"font-size":{"font-size":13},"background-color":{"background-color":{"r":255,"g":255,"b":255}}},{"id":"4","text":"RESEARCH","width":{"width":94},"height":{"height":22},"x":{"left":459,"right":926},"y":{"top":99,"bottom":679},"font-size":{"font-size":13},"background-color":{"background-color":{"r":255,"g":255,"b":255}}},{"id":"5","text":"PEOPLE","width":{"width":74},"height":{"height":21},"x":{"left":566,"right":838},"y":{"top":99,"bottom":680},"font-size":{"font-size":13},"background-color":{"background-color":{"r":255,"g":255,"b":255}}},{"id":"6","text":"INDUSTRY","width":{"width":92},"height":{"height":21},"x":{"left":655,"right":731},"y":{"top":99,"bottom":680},"font-size":{"font-size":13},"background-color":{"background-color":{"r":255,"g":255,"b":255}}},{"id":"7","text":"NEWS+AWARDS","width":{"width":131},"height":{"height":20},"x":{"left":764,"right":584},"y":{"top":99,"bottom":681},"font-size":{"font-size":13},"background-color":{"background-color":{"r":255,"g":255,"b":255}}},{"id":"8","text":"EVENTS","width":{"width":74},"height":{"height":20},"x":{"left":905,"right":500},"y":{"top":99,"bottom":681},"font-size":{"font-size":13},"background-color":{"background-color":{"r":255,"g":255,"b":255}}},{"id":"9","text":"","image":"images/cse-slide-dsms3.jpg","width":{"width":1021},"height":{"height":165},"x":{"left":237,"right":221},"y":{"top":211,"bottom":423},"font-size":{"font-size":16},"background-color":{"background-color":{"r":255,"g":255,"b":255}}}],"pageWidth":1480,"pageHeight":800,"id":0},"1":{"elements":[{"id":"0","text":"","width":{"width":1019},"height":{"height":89},"x":{"left":4,"right":7},"y":{"top":4,"bottom":707},"font-size":{"font-size":16},"background-color":{"background-color":{"r":12,"g":50,"b":84}}},{"id":"1","text":"","width":{"width":1018},"height":{"height":35},"x":{"left":4,"right":8},"y":{"top":94,"bottom":671},"font-size":{"font-size":16},"background-color":{"background-color":{"r":56,"g":82,"b":109}}},{"id":"2","text":"","image":"images/cse_logo.png","width":{"width":430},"height":{"height":82},"x":{"left":0,"right":601},"y":{"top":7,"bottom":711},"font-size":{"font-size":16},"background-color":{"background-color":{"r":255,"g":255,"b":255}}},{"id":"3","text":"ACADEMICS+ADMISSIONS","width":{"width":207},"height":{"height":21},"x":{"left":0,"right":822},"y":{"top":99,"bottom":680},"font-size":{"font-size":12},"background-color":{"background-color":{"r":255,"g":255,"b":255}}},{"id":"4","text":"RESEARCH","width":{"width":93},"height":{"height":22},"x":{"left":225,"right":711},"y":{"top":99,"bottom":679},"font-size":{"font-size":12},"background-color":{"background-color":{"r":255,"g":255,"b":255}}},{"id":"5","text":"PEOPLE","width":{"width":73},"height":{"height":21},"x":{"left":337,"right":619},"y":{"top":99,"bottom":680},"font-size":{"font-size":12},"background-color":{"background-color":{"r":255,"g":255,"b":255}}},{"id":"6","text":"INDUSTRY","width":{"width":91},"height":{"height":21},"x":{"left":430,"right":508},"y":{"top":99,"bottom":680},"font-size":{"font-size":12},"background-color":{"background-color":{"r":255,"g":255,"b":255}}},{"id":"7","text":"NEWS+AWARDS","width":{"width":130},"height":{"height":20},"x":{"left":543,"right":356},"y":{"top":99,"bottom":681},"font-size":{"font-size":12},"background-color":{"background-color":{"r":255,"g":255,"b":255}}},{"id":"8","text":"EVENTS","width":{"width":73},"height":{"height":20},"x":{"left":689,"right":267},"y":{"top":99,"bottom":681},"font-size":{"font-size":12},"background-color":{"background-color":{"r":255,"g":255,"b":255}}},{"id":"9","text":"","image":"images/cse-slide-dsms3.jpg","width":{"width":1021},"height":{"height":165},"x":{"left":0,"right":10},"y":{"top":211,"bottom":423},"font-size":{"font-size":16},"background-color":{"background-color":{"r":255,"g":255,"b":255}}}],"pageWidth":1031,"pageHeight":800,"id":1},"5":{"elements":[{"id":"0","text":"","width":{"width":654},"height":{"height":89},"x":{"left":4,"right":3},"y":{"top":4,"bottom":707},"font-size":{"font-size":16},"background-color":{"background-color":{"r":12,"g":50,"b":84}}},{"id":"1","text":"","width":{"width":653},"height":{"height":35},"x":{"left":4,"right":4},"y":{"top":94,"bottom":671},"font-size":{"font-size":16},"background-color":{"background-color":{"r":56,"g":82,"b":109}}},{"id":"2","text":"","image":"images/cse_logo.png","width":{"width":430},"height":{"height":82},"x":{"left":3,"right":228},"y":{"top":7,"bottom":711},"font-size":{"font-size":16},"background-color":{"background-color":{"r":255,"g":255,"b":255}}},{"id":"3","text":"ACADEMICS+ADMISSIONS","width":{"width":156},"height":{"height":21},"x":{"left":4,"right":501},"y":{"top":99,"bottom":680},"font-size":{"font-size":9},"background-color":{"background-color":{"r":255,"g":255,"b":255}}},{"id":"4","text":"RESEARCH","width":{"width":68},"height":{"height":22},"x":{"left":174,"right":419},"y":{"top":99,"bottom":679},"font-size":{"font-size":9},"background-color":{"background-color":{"r":255,"g":255,"b":255}}},{"id":"5","text":"PEOPLE","width":{"width":51},"height":{"height":21},"x":{"left":256,"right":354},"y":{"top":99,"bottom":680},"font-size":{"font-size":9},"background-color":{"background-color":{"r":255,"g":255,"b":255}}},{"id":"6","text":"INDUSTRY","width":{"width":66},"height":{"height":21},"x":{"left":320,"right":275},"y":{"top":99,"bottom":680},"font-size":{"font-size":9},"background-color":{"background-color":{"r":255,"g":255,"b":255}}},{"id":"7","text":"NEWS+AWARDS","width":{"width":94},"height":{"height":20},"x":{"left":403,"right":164},"y":{"top":99,"bottom":681},"font-size":{"font-size":9},"background-color":{"background-color":{"r":255,"g":255,"b":255}}},{"id":"8","text":"EVENTS","width":{"width":55},"height":{"height":20},"x":{"left":512,"right":94},"y":{"top":99,"bottom":681},"font-size":{"font-size":9},"background-color":{"background-color":{"r":255,"g":255,"b":255}}},{"id":"9","text":"","image":"images/cse-slide-dsms3.jpg","width":{"width":644},"height":{"height":165},"x":{"left":3,"right":13},"y":{"top":211,"bottom":423},"font-size":{"font-size":16},"background-color":{"background-color":{"r":255,"g":255,"b":255}}}],"pageWidth":662,"pageHeight":800,"id":5}}}